keras_lr_finder/__init__.py
keras_lr_finder/lr_finder.py
keras_lr_finder-0.1.dist-info/DESCRIPTION.rst
keras_lr_finder-0.1.dist-info/METADATA
keras_lr_finder-0.1.dist-info/RECORD
keras_lr_finder-0.1.dist-info/WHEEL
keras_lr_finder-0.1.dist-info/metadata.json
keras_lr_finder-0.1.dist-info/top_level.txt
