Metadata-Version: 2.0
Name: keras-lr-finder
Version: 0.1
Summary: Learning rate finder for Keras.
Home-page: https://github.com/surmenok/keras_lr_finder
Author: Pavel Surmenok
Author-email: pavel@surmenok.com
License: MIT
Platform: UNKNOWN
Requires-Dist: keras (>=2.0.0)
Requires-Dist: matplotlib
